finnomena_api/__init__.py
finnomena_api/api.py
finnomena_api/keys.py
finnomena_api/utils.py
finnomena_api-1.0.5.dist-info/LICENSE
finnomena_api-1.0.5.dist-info/METADATA
finnomena_api-1.0.5.dist-info/WHEEL
finnomena_api-1.0.5.dist-info/top_level.txt
finnomena_api-1.0.5.dist-info/RECORD
